prompthandler/__init__.py
prompthandler/models.py
prompthandler/prompts.py
prompthandler-0.3.3.dist-info/LICENSE
prompthandler-0.3.3.dist-info/METADATA
prompthandler-0.3.3.dist-info/WHEEL
prompthandler-0.3.3.dist-info/top_level.txt
prompthandler-0.3.3.dist-info/RECORD
