Metadata-Version: 2.1
Name: prompthandler
Version: 0.3.3
Summary: Token Management system for chatgpt and more. Keeps your prompt under token with summary support
Author: prasannan-robots
License: MIT License
Keywords: openai chatgpt prompts summarizer handler summary token gpt-4
Classifier: Programming Language :: Python :: 3
Classifier: License :: OSI Approved :: MIT License
Classifier: Operating System :: OS Independent
License-File: LICENSE
Requires-Dist: openai
Requires-Dist: tiktoken
